acq4_autopatch/__init__.py
acq4_autopatch/job_queue.py
acq4_autopatch/module.py
acq4_autopatch/patch_attempt.py
acq4_autopatch/patch_thread.py
acq4_autopatch/devices/AutopatchCustomStage.py
acq4_autopatch/devices/__init__.py
acq4_autopatch/devices/custom_motion_planners.py
acq4_autopatch/devices/custom_patch_states.py
acq4_autopatch/protocols/__init__.py
acq4_autopatch/protocols/mock.py
acq4_autopatch/protocols/patch_protocol.py
acq4_autopatch/protocols/recalibrate.py
acq4_autopatch/protocols/task_runner.py
acq4_autopatch/protocols/test.py
acq4_autopatch-0.0.4.dist-info/METADATA
acq4_autopatch-0.0.4.dist-info/WHEEL
acq4_autopatch-0.0.4.dist-info/top_level.txt
acq4_autopatch-0.0.4.dist-info/RECORD
