Metadata-Version: 2.1
Name: acq4-autopatch
Version: 0.0.4
Summary: Automated cell patching extension for ACQ4
Home-page: https://github.com/sensapex/acq4-autopatch
Author: Luke Campagnola
Author-email: luke.campagnola@gmail.com
License: LGPL-3
Platform: UNKNOWN
Classifier: Development Status :: 4 - Beta
Classifier: Environment :: Other Environment
Classifier: Intended Audience :: Science/Research
Classifier: License :: OSI Approved :: GNU General Public License v3 (GPLv3)
Classifier: Operating System :: OS Independent
Classifier: Programming Language :: Python :: 3
Classifier: Programming Language :: Python
Classifier: Topic :: Scientific/Engineering
Classifier: Topic :: Software Development :: Libraries :: Python Modules
Requires-Dist: acq4
